bindings/bstream.cpp
bstream/__init__.py
bstream/_bstream.cpython-38-aarch64-linux-gnu.so
bstream/_bstream.pyi
tests/test.py
bstream-1.0.1.dist-info/LICENSE
bstream-1.0.1.dist-info/METADATA
bstream-1.0.1.dist-info/WHEEL
bstream-1.0.1.dist-info/top_level.txt
bstream-1.0.1.dist-info/RECORD
